couchclient
