Metadata-Version: 1.0
Name: couchclient
Version: 1.1.1
Summary: Light-weight read-only CouchDB client for loading documents and views
Home-page: http://github.com/gmr/couchclient
Author: Gavin M. Roy
Author-email: gmr@myyearbook.com
License: UNKNOWN
Platform: UNKNOWN
Classifier: Development Status :: 4 - Beta
Classifier: Intended Audience :: Developers
Classifier: Programming Language :: Python :: 2.5
Classifier: Programming Language :: Python :: 2.6
Classifier: Programming Language :: Python :: 2.7
Classifier: Topic :: Internet :: WWW/HTTP
Classifier: Topic :: Software Development :: Libraries
Classifier: Topic :: Software Development :: Libraries :: Python Modules
Classifier: License :: OSI Approved :: BSD License
